yougotmail/__init__.py
yougotmail/_utils/__init__.py
yougotmail/_utils/_ms_webhook.py
yougotmail/_utils/_utils.py
yougotmail/_utils/_validation.py
yougotmail/ai/__init__.py
yougotmail/ai/_ai_handler.py
yougotmail/ai/_ai_prompts.py
yougotmail/ai/_ai_schemas.py
yougotmail/ai/_ai_tools.py
yougotmail/ai/ai.py
yougotmail/move/__init__.py
yougotmail/move/move_delete.py
yougotmail/quick/__init__.py
yougotmail/quick/quick.py
yougotmail/retrieve/__init__.py
yougotmail/retrieve/retrieval_utils.py
yougotmail/retrieve/retrieve_attachments.py
yougotmail/retrieve/retrieve_conversations.py
yougotmail/retrieve/retrieve_emails.py
yougotmail/router/__init__.py
yougotmail/router/router.py
yougotmail/send/__init__.py
yougotmail/send/reply.py
yougotmail/send/send.py
yougotmail/storage/__init__.py
yougotmail/storage/storage.py
yougotmail-0.0.15.dist-info/LICENSE
yougotmail-0.0.15.dist-info/METADATA
yougotmail-0.0.15.dist-info/WHEEL
yougotmail-0.0.15.dist-info/top_level.txt
yougotmail-0.0.15.dist-info/RECORD
