Metadata-Version: 2.1
Name: yougotmail
Version: 0.0.15
Summary: Easily create AI Agents in MS Outlook
Home-page: https://github.com/WitoldKowalczyk/YouGotMail
Author: Witold Kowalczyk
Author-email: witold@delosintelligence.com
Classifier: Programming Language :: Python :: 3.10
Classifier: License :: OSI Approved :: Apache Software License
Classifier: Operating System :: OS Independent
Requires-Python: >=3.10.12
License-File: LICENSE
Requires-Dist: requests
Requires-Dist: python-dateutil
Provides-Extra: boto3
Requires-Dist: boto3 ; extra == 'boto3'
Provides-Extra: openai
Requires-Dist: openai ; extra == 'openai'
Provides-Extra: pymongo
Requires-Dist: pymongo ; extra == 'pymongo'
